chichicha/__init__.py
chichicha/libusb-1.0.dll
chichicha/pywpc.cp310-win_amd64.pyd
chichicha/pywpc.cp38-win_amd64.pyd
chichicha/pywpc.cp39-win_amd64.pyd
chichicha/pywpc.cpython-310-x86_64-linux-gnu.so
chichicha/pywpc.pyd
chichicha/version.py
chichicha-2.5.0.dist-info/LICENSE
chichicha-2.5.0.dist-info/METADATA
chichicha-2.5.0.dist-info/WHEEL
chichicha-2.5.0.dist-info/top_level.txt
chichicha-2.5.0.dist-info/RECORD
